inscriptis/__init__.py
inscriptis/annotation/__init__.py
inscriptis/annotation/output/__init__.py
inscriptis/annotation/output/html.py
inscriptis/annotation/output/surface.py
inscriptis/annotation/output/xml.py
inscriptis/annotation/parser.py
inscriptis/cli/__init__.py
inscriptis/cli/inscript.py
inscriptis/css_profiles.py
inscriptis/html_engine.py
inscriptis/html_properties.py
inscriptis/metadata.py
inscriptis/model/__init__.py
inscriptis/model/attribute.py
inscriptis/model/canvas/__init__.py
inscriptis/model/canvas/block.py
inscriptis/model/canvas/prefix.py
inscriptis/model/config.py
inscriptis/model/css.py
inscriptis/model/html_document_state.py
inscriptis/model/html_element.py
inscriptis/model/table.py
inscriptis/model/tag/__init__.py
inscriptis/model/tag/a_tag.py
inscriptis/model/tag/br_tag.py
inscriptis/model/tag/img_tag.py
inscriptis/model/tag/list_tag.py
inscriptis/model/tag/table_tag.py
inscriptis/service/__init__.py
inscriptis/service/web.py
inscriptis-2.5.2.dist-info/AUTHORS
inscriptis-2.5.2.dist-info/LICENSE
inscriptis-2.5.2.dist-info/METADATA
inscriptis-2.5.2.dist-info/WHEEL
inscriptis-2.5.2.dist-info/entry_points.txt
inscriptis-2.5.2.dist-info/RECORD
