Metadata-Version: 2.1
Name: inscriptis
Version: 2.5.2
Summary: inscriptis - HTML to text converter.
Home-page: https://github.com/weblyzard/inscriptis
License: Apache-2.0
Keywords: HTML,converter,text
Author: Albert Weichselbraun
Author-email: albert.weichselbraun@fhgr.ch
Requires-Python: >=3.9,<4.0
Classifier: Development Status :: 5 - Production/Stable
Classifier: Intended Audience :: Developers
Classifier: License :: OSI Approved :: Apache Software License
Classifier: Programming Language :: Python :: 3
Classifier: Programming Language :: Python :: 3.9
Classifier: Programming Language :: Python :: 3.10
Classifier: Programming Language :: Python :: 3.11
Classifier: Programming Language :: Python :: 3.12
Classifier: Programming Language :: Python :: 3.13
Classifier: Topic :: Text Processing
Classifier: Topic :: Text Processing :: Markup :: HTML
Classifier: Topic :: Utilities
Provides-Extra: web-service
Requires-Dist: fastapi (>=0.109.1,<0.110.0) ; extra == "web-service"
Requires-Dist: lxml (>=4.9.3)
Requires-Dist: requests (==2.32.2)
Requires-Dist: uvicorn (>=0.27.1,<0.28.0) ; extra == "web-service"
Project-URL: Documentation, https://inscriptis.readthedocs.io/en
Project-URL: Repository, https://github.com/weblyzard/inscriptis
